pyuoi/__init__.py
pyuoi/mpi_utils.py
pyuoi/utils.py
pyuoi/data/Swimmer.h5
pyuoi/datasets/__init__.py
pyuoi/decomposition/CUR.py
pyuoi/decomposition/NMF.py
pyuoi/decomposition/__init__.py
pyuoi/decomposition/base.py
pyuoi/decomposition/utils.py
pyuoi/lbfgs/__init__.py
pyuoi/lbfgs/_lowlevel.cpython-37m-darwin.so
pyuoi/linear_model/__init__.py
pyuoi/linear_model/base.py
pyuoi/linear_model/elasticnet.py
pyuoi/linear_model/lasso.py
pyuoi/linear_model/logistic.py
pyuoi/linear_model/poisson.py
pyuoi/linear_model/utils.py
pyuoi-1.0.0.dist-info/LICENSE.txt
pyuoi-1.0.0.dist-info/METADATA
pyuoi-1.0.0.dist-info/WHEEL
pyuoi-1.0.0.dist-info/top_level.txt
pyuoi-1.0.0.dist-info/RECORD
