Metadata-Version: 2.1
Name: pyuoi
Version: 1.0.0
Summary: The Union of Intersections framework in Python.
Home-page: https://github.com/BouchardLab/pyuoi
Author: 
Author-email: 
License: UNKNOWN
Keywords: UoI
Platform: UNKNOWN
Classifier: Development Status :: 4 - Beta
Classifier: Intended Audience :: Science/Research
Classifier: Topic :: Scientific/Engineering
Classifier: License :: OSI Approved :: BSD License
Classifier: Programming Language :: Python :: 3
Classifier: Programming Language :: Python :: 3.6
Classifier: Programming Language :: Python :: 3.7
Classifier: Programming Language :: Python :: 3.8
Requires-Dist: numpy (>=1.14)
Requires-Dist: h5py (>=2.8)
Requires-Dist: scikit-learn (>=0.20)
Provides-Extra: dev
Requires-Dist: pytest ; extra == 'dev'
Requires-Dist: flake8 ; extra == 'dev'
Requires-Dist: cython ; extra == 'dev'
Requires-Dist: sphinx-gallery ; extra == 'dev'
Requires-Dist: sphinx-rtd-theme ; extra == 'dev'
Provides-Extra: perf
Requires-Dist: mpi4py ; extra == 'perf'
Requires-Dist: pycasso ; extra == 'perf'
